chat_transformer/__init__.py
chat_transformer/cli.py
chat_transformer/client.py
chat_transformer/commands.py
chat_transformer/responses.py
chat_transformer/utils.py
chat_transformer/watchers.py
chat_transformer/outputs/__init__.py
chat_transformer/outputs/base.py
chat_transformer/outputs/http.py
chat_transformer/outputs/osc.py
chat_transformer/outputs/udp.py
chat_transformer-0.5.0.dist-info/METADATA
chat_transformer-0.5.0.dist-info/RECORD
chat_transformer-0.5.0.dist-info/WHEEL
chat_transformer-0.5.0.dist-info/entry_points.txt
chat_transformer-0.5.0.dist-info/top_level.txt
tests/__init__.py
tests/test_client.py
tests/test_commands.py
tests/test_http.py
tests/test_responses.py
