Metadata-Version: 2.1
Name: chat-transformer
Version: 0.5.0
Summary: Bridge that takes incoming IRC messages and converts them to other formats
Home-page: https://github.com/MattBroach/chat_transformer
Author: Matt Nishi-Broach
Author-email: go.for.dover@gmail.com
License: MIT
Platform: UNKNOWN
Classifier: Environment :: Web Environment
Classifier: Intended Audience :: Developers
Classifier: License :: OSI Approved :: MIT License
Classifier: Operating System :: OS Independent
Classifier: Programming Language :: Python :: 3
Classifier: Programming Language :: Python :: 3.5
Classifier: Programming Language :: Python :: 3.6
Classifier: Topic :: Communications :: Chat :: Internet Relay Chat
Classifier: Topic :: Multimedia
Requires-Python: >=3.5.3
Requires-Dist: irc (>=16.4)
Requires-Dist: python-osc (>=1.6.6)
Requires-Dist: aiohttp (>=3.3.2)
Requires-Dist: PyJWT (==1.6.4)
